galaxy/__init__.py
galaxy/project_galaxy_test_tools.py
galaxy/test_tools/README.txt
galaxy/test_tools/__init__.py
galaxy/test_tools/bibtex.xml
galaxy/test_tools/boolean_conditional.xml
galaxy/test_tools/catDocker.xml
galaxy/test_tools/cat_data_and_sleep.xml
galaxy/test_tools/checksum.xml
galaxy/test_tools/cheetah_casting.xml
galaxy/test_tools/cheetah_problem_syntax_error.xml
galaxy/test_tools/cheetah_problem_unbound_var.xml
galaxy/test_tools/cheetah_problem_unbound_var_input.xml
galaxy/test_tools/code_file.py
galaxy/test_tools/code_file.xml
galaxy/test_tools/collection_cat_group_tag.xml
galaxy/test_tools/collection_cat_group_tag_multiple.xml
galaxy/test_tools/collection_creates_dynamic_list_of_pairs.xml
galaxy/test_tools/collection_creates_dynamic_nested.xml
galaxy/test_tools/collection_creates_dynamic_nested_fail.xml
galaxy/test_tools/collection_creates_dynamic_nested_from_json.xml
galaxy/test_tools/collection_creates_dynamic_nested_from_json_elements.xml
galaxy/test_tools/collection_creates_list.xml
galaxy/test_tools/collection_creates_list_2.xml
galaxy/test_tools/collection_creates_list_fail.xml
galaxy/test_tools/collection_creates_list_of_pairs.xml
galaxy/test_tools/collection_creates_pair.xml
galaxy/test_tools/collection_creates_pair_from_type.xml
galaxy/test_tools/collection_creates_pair_y.yml
galaxy/test_tools/collection_mixed_param.xml
galaxy/test_tools/collection_nested_test.xml
galaxy/test_tools/collection_optional_param.xml
galaxy/test_tools/collection_paired_conditional_structured_like.xml
galaxy/test_tools/collection_paired_structured_like.xml
galaxy/test_tools/collection_paired_test.xml
galaxy/test_tools/collection_split_on_column.xml
galaxy/test_tools/collection_two_paired.xml
galaxy/test_tools/collection_type_source.xml
galaxy/test_tools/collection_type_source_map_over.xml
galaxy/test_tools/color_param.xml
galaxy/test_tools/column_multi_param.xml
galaxy/test_tools/column_param.xml
galaxy/test_tools/column_param_configfile.xml
galaxy_test_tools-19.9.0.dev2.dist-info/LICENSE
galaxy_test_tools-19.9.0.dev2.dist-info/METADATA
galaxy_test_tools-19.9.0.dev2.dist-info/WHEEL
galaxy_test_tools-19.9.0.dev2.dist-info/entry_points.txt
galaxy_test_tools-19.9.0.dev2.dist-info/top_level.txt
galaxy_test_tools-19.9.0.dev2.dist-info/RECORD
